desam_client/__init__.py
desam_client/client.py
desam_client/exceptions.py
desam_client/models.py
desam_client/_grpc/__init__.py
desam_client/_grpc/client.proto
desam_client/_grpc/client_pb2.py
desam_client/_grpc/client_pb2_grpc.py
desam_client/file_transfer/__init__.py
desam_client/file_transfer/checksum.py
desam_client/file_transfer/compression.py
desam_client/file_transfer/manager.py
desam_client/file_transfer/models.py
desam_client-0.1.1.dist-info/METADATA
desam_client-0.1.1.dist-info/WHEEL
desam_client-0.1.1.dist-info/licenses/LICENSE
desam_client-0.1.1.dist-info/RECORD
