Metadata-Version: 2.4
Name: desam-client
Version: 0.1.1
Summary: DeSAM调度器Python客户端库
Project-URL: Homepage, https://github.com/QiandingHuang666/DeSAM_client
Project-URL: Documentation, https://github.com/QiandingHuang666/DeSAM_client/tree/main/DeSAM_client
Project-URL: Repository, https://github.com/QiandingHuang666/DeSAM_client.git
Project-URL: Issues, https://github.com/QiandingHuang666/DeSAM_client/issues
Author-email: QD Huang <qiandinghuang666@gamil.com>
Maintainer-email: QD Huang <qiandinghuang666@gamil.com>
License: Apache-2.0
License-File: LICENSE
Keywords: desam,grpc,job-queue,scheduler
Classifier: Development Status :: 4 - Beta
Classifier: Intended Audience :: Developers
Classifier: License :: OSI Approved :: Apache Software License
Classifier: Operating System :: OS Independent
Classifier: Programming Language :: Python :: 3
Classifier: Programming Language :: Python :: 3.8
Classifier: Programming Language :: Python :: 3.9
Classifier: Programming Language :: Python :: 3.10
Classifier: Programming Language :: Python :: 3.11
Classifier: Programming Language :: Python :: 3.12
Classifier: Topic :: Software Development :: Libraries :: Python Modules
Requires-Python: >=3.8.1
Requires-Dist: build>=1.2.2.post1
Requires-Dist: grpcio-tools>=1.60.0
Requires-Dist: grpcio>=1.60.0
Requires-Dist: protobuf>=4.25.0
Requires-Dist: twine>=6.1.0
Provides-Extra: dev
Requires-Dist: bandit>=1.7.0; extra == 'dev'
Requires-Dist: black>=23.0.0; extra == 'dev'
Requires-Dist: flake8>=6.0.0; extra == 'dev'
Requires-Dist: isort>=5.12.0; extra == 'dev'
Requires-Dist: mypy>=1.5.0; extra == 'dev'
Requires-Dist: pytest-cov>=4.0.0; extra == 'dev'
Requires-Dist: pytest>=7.0.0; extra == 'dev'
Requires-Dist: safety>=3.0.0; extra == 'dev'
